path_jail-0.2.0.dist-info/METADATA
path_jail-0.2.0.dist-info/WHEEL
path_jail-0.2.0.dist-info/licenses/LICENSE-APACHE
path_jail-0.2.0.dist-info/licenses/LICENSE-MIT
path_jail/__init__.py
path_jail/__init__.pyi
path_jail/path_jail.abi3.so
path_jail/py.typed
path_jail-0.2.0.dist-info/RECORD
