Metadata-Version: 2.4
Name: path-jail
Version: 0.2.0
Classifier: Development Status :: 4 - Beta
Classifier: Intended Audience :: Developers
Classifier: License :: OSI Approved :: MIT License
Classifier: License :: OSI Approved :: Apache Software License
Classifier: Programming Language :: Python :: 3
Classifier: Programming Language :: Python :: 3.9
Classifier: Programming Language :: Python :: 3.10
Classifier: Programming Language :: Python :: 3.11
Classifier: Programming Language :: Python :: 3.12
Classifier: Programming Language :: Python :: 3.13
Classifier: Programming Language :: Rust
Classifier: Topic :: Security
Classifier: Typing :: Typed
Requires-Dist: pytest>=7.0 ; extra == 'dev'
Requires-Dist: ruff>=0.4 ; extra == 'dev'
Requires-Dist: mypy>=1.0 ; extra == 'dev'
Provides-Extra: dev
License-File: LICENSE-APACHE
License-File: LICENSE-MIT
Summary: Secure filesystem sandbox. Restricts paths to a root directory, preventing traversal attacks.
Keywords: security,filesystem,sandbox,path,traversal
Home-Page: https://tenuo.dev
License: MIT OR Apache-2.0
Requires-Python: >=3.9
Project-URL: Homepage, https://tenuo.dev
Project-URL: Repository, https://github.com/tenuo-ai/path-jail-python
Project-URL: Documentation, https://github.com/tenuo-ai/path-jail-python#readme
